LICENSE
MANIFEST.in
README.md
VERSION
setup.cfg
setup.py
src/cltl.triple_extraction.egg-info/PKG-INFO
src/cltl.triple_extraction.egg-info/SOURCES.txt
src/cltl.triple_extraction.egg-info/dependency_links.txt
src/cltl.triple_extraction.egg-info/requires.txt
src/cltl.triple_extraction.egg-info/top_level.txt
src/cltl/question_extraction/__init__.py
src/cltl/question_extraction/analyzer.py
src/cltl/question_extraction/cfg_question_analyzer.py
src/cltl/question_extraction/stanza_question_analyzer.py
src/cltl/question_extraction/question_to_statement/POSTree.py
src/cltl/question_extraction/question_to_statement/__init__.py
src/cltl/triple_extraction/__init__.py
src/cltl/triple_extraction/analyzer.py
src/cltl/triple_extraction/api.py
src/cltl/triple_extraction/cfg_analyzer.py
src/cltl/triple_extraction/chat_analyzer.py
src/cltl/triple_extraction/conversational_analyzer.py
src/cltl/triple_extraction/oie_analyzer.py
src/cltl/triple_extraction/spacy_analyzer.py
src/cltl/triple_extraction/conversational_triples/argument_extraction.py
src/cltl/triple_extraction/conversational_triples/conversational_triple_extraction.py
src/cltl/triple_extraction/conversational_triples/post_processing.py
src/cltl/triple_extraction/conversational_triples/triple_scoring.py
src/cltl/triple_extraction/conversational_triples/utils.py
src/cltl/triple_extraction/conversational_triples/predicate_normalization/evaluate_predicate_normalization.py
src/cltl/triple_extraction/conversational_triples/predicate_normalization/predicate_normalization.py
src/cltl/triple_extraction/nlp/__init__.py
src/cltl/triple_extraction/nlp/name.py
src/cltl/triple_extraction/nlp/ner.py
src/cltl/triple_extraction/nlp/parser.py
src/cltl/triple_extraction/nlp/pos.py
src/cltl/triple_extraction/nlp/transitivity.py
src/cltl/triple_extraction/spacy_triples/dep_to_triple.py
src/cltl/triple_extraction/stanford-ner/LICENSE.txt
src/cltl/triple_extraction/stanford-ner/english.all.3class.distsim.crf.ser
src/cltl/triple_extraction/stanford-ner/english.muc.7class.distsim.crf.ser
src/cltl/triple_extraction/stanford-ner/stanford-ner.jar
src/cltl/triple_extraction/stanford-pos/LICENSE.txt
src/cltl/triple_extraction/stanford-pos/README.txt
