Metadata-Version: 2.1
Name: cltl.triple-extraction
Version: 2.0.dev1
Summary: The Leolani Language module for knowledge extraction
Home-page: https://github.com/leolani/cltl-knowledgeextraction
License: MIT License
Requires-Python: >=3.7
License-File: LICENSE
Requires-Dist: nltk~=3.4
Requires-Dist: stanford_openie~=1.3
Requires-Dist: spacy~=3.2
Requires-Dist: stanza~=1.5
Requires-Dist: cltl.combot~=1.0.dev0
Provides-Extra: service
Requires-Dist: cltl.combot; extra == "service"
